rvt_detector.py
rvt_detector-0.6.0.dist-info/LICENSE
rvt_detector-0.6.0.dist-info/WHEEL
rvt_detector-0.6.0.dist-info/METADATA
rvt_detector-0.6.0.dist-info/RECORD
